pseudofinch/Finch.py
pseudofinch/__init__.py
pseudofinch-1.0.0.dist-info/LICENSE
pseudofinch-1.0.0.dist-info/METADATA
pseudofinch-1.0.0.dist-info/WHEEL
pseudofinch-1.0.0.dist-info/top_level.txt
pseudofinch-1.0.0.dist-info/RECORD
