Metadata-Version: 2.2
Name: pseudofinch
Version: 1.0.0
Summary: An emulation library inspired by the Finch 2.0 made by BirdBrain Technologies.
Author-email: Quinn Pare' <quinnpare@gmail.com>
License: MPL2.0
Project-URL: Homepage, https://github.com/quibbious/PseudoFinch
Project-URL: Issues, https://github.com/quibbious/PseudoFinch/issues
Classifier: Programming Language :: Python :: 3
Classifier: Operating System :: OS Independent
Requires-Python: >=3.12
License-File: LICENSE
